wandb_utils/__init__.py
wandb_utils/__main__.py
wandb_utils/config.py
wandb_utils/misc.py
wandb_utils/version.py
wandb_utils/api/__init__.py
wandb_utils/api/all_data.py
wandb_utils/api/client.py
wandb_utils/commands/__init__.py
wandb_utils/commands/all_data.py
wandb_utils/commands/backup.py
wandb_utils/commands/best_models.py
wandb_utils/commands/common.py
wandb_utils/commands/download_from_wandb.py
wandb_utils/commands/files.py
wandb_utils/commands/filter.py
wandb_utils/commands/from_file.py
wandb_utils/commands/multiple_runs.py
wandb_utils/commands/print.py
wandb_utils/commands/remove_files_from_server.py
wandb_utils/commands/run_dir.py
wandb_utils/commands/slurm.py
wandb_utils/commands/wandb_utils.py
wandb_utils/file_filter/__init__.py
wandb_utils/file_filter/file_filter.py
wandb_utils/file_filter/glob_filter.py
wandb_utils/run_filter/__init__.py
wandb_utils/run_filter/name_filter.py
wandb_utils/run_filter/run_filter.py
wandb_utils-0.1.2.dist-info/LICENSE
wandb_utils-0.1.2.dist-info/METADATA
wandb_utils-0.1.2.dist-info/WHEEL
wandb_utils-0.1.2.dist-info/entry_points.txt
wandb_utils-0.1.2.dist-info/top_level.txt
wandb_utils-0.1.2.dist-info/RECORD
