Metadata-Version: 2.1
Name: wandb-utils
Version: 0.1.2
Summary: Utitlity functions and scripts to work with Weights \& Biases
Home-page: http://www.dhruveshp.com/wandb-utils
Author: Dhruvesh Patel
Author-email: 1793dnp@gmail.com
License: UNKNOWN
Project-URL: Documentation, https://wandb-utils.readthedocs.io
Project-URL: Source Code, https://github.com/dhruvdcoder/wandb-utils
Keywords: AI,ML,Optimization,Machine Learning,Deep Learning
Platform: UNKNOWN
Classifier: Programming Language :: Python :: 3
Classifier: License :: OSI Approved :: MIT License
Classifier: Operating System :: OS Independent
Classifier: Development Status :: 3 - Alpha
Classifier: Intended Audience :: Developers
Classifier: Intended Audience :: Science/Research
Classifier: Natural Language :: English
Requires-Python: >=3.7
License-File: LICENSE
Requires-Dist: wandb
Requires-Dist: ruamel.yaml
Requires-Dist: click (>=8.0.1)
Requires-Dist: click-option-group
Requires-Dist: click-config-file
Requires-Dist: PyClone
Requires-Dist: tqdm
Requires-Dist: pandas
Requires-Dist: jinja2schema
